Workbook

Sheet Start Here
A1: Databricks Data Engineering Journey — 6-Month Learning Tracker
A2: 26 weeks • ~10 hours/week • ~260 planned hours • Python, NumPy, Pandas, PySpark, Databricks and Delta Lake
A4: How to use this workbook
A5: 1. Start with the 26-Week Roadmap sheet to see the weekly concepts, resources, project and expected deliverable.
A6: 2. In Daily Tracker, enter a planned date if useful, then update Actual Hours, Status and Notes after each session.
A7: 3. Status options: Not Started, In Progress, Blocked, Completed. Use the notes column to record links, blockers and lessons.
A8: 4. Planned hours are allocated as 1.5 hours for Days 1–6 and 1 hour for Day 7 = 10 hours/week. Move sessions around as needed.
A9: 5. Use the Progress Dashboard to track completion. Completion is based on marking daily tasks Completed.
A10: 6. Free-tier/platform features and URLs can change. Check current Databricks Free Edition limits before planning compute-heavy exercises.
A11: 7. Do not upload employer/client data or confidential code to a public repository. Use synthetic/public datasets.
A14: Suggested weekly routine
A15: Days 1–2 | B15: Concepts + guided examples | C15: 3 hours
A16: Days 3–5 | B16: Exercises + realistic data + debugging | C16: 4.5 hours
A17: Day 6 | B17: Mini-project implementation | C17: 1.5 hours
A18: Day 7 | B18: Finish deliverable + review | C18: 1 hour
A21: Learning outcome after 6 months
A22: Target: working proficiency to build, test, troubleshoot and explain a production-style lakehouse pipeline. Advanced mastery requires continued practice beyond the planned 260 hours.

Sheet Progress Dashboard
A1: Learning Progress Dashboard
A3: Overall Metrics
A4: Planned learning hours | B4: =SUM('Daily Tracker'!G2:G183) -> 260
A5: Actual learning hours | B5: =SUM('Daily Tracker'!I2:I183) -> 0
A6: Daily sessions completed | B6: =COUNTIF('Daily Tracker'!J2:J183,"Completed") -> 0
A7: Total daily sessions | B7: =COUNTA('Daily Tracker'!A2:A183) -> 182
A8: Completion percentage | B8: =IF(B7=0,0,B6/B7) -> 0
A9: Hours progress percentage | B9: =IF(B4=0,0,B5/B4) -> 0
A12: Progress by week
A13: Week | B13: Theme | C13: Completed sessions | D13: Total sessions | E13: Actual hours | F13: Status
A14: 1 | B14: Python basics and programming logic | C14: 0 | D14: =COUNTIF('Daily Tracker'!$A$2:$A$183,A14) -> 7 | E14: 0 | F14: =IF(C14=D14,"Completed",IF(C14=0,"Not Started","In Progress")) -> Not Started
A15: 2 | B15: Data structures and functions | C15: =COUNTIFS('Daily Tracker'!$A$2:$A$183,A15,'Daily Tracker'!$J$2:$J$183,"Completed") -> 0 | D15: =COUNTIF('Daily Tracker'!$A$2:$A$183,A15) -> 7 | E15: =SUMIF('Daily Tracker'!$A$2:$A$183,A15,'Daily Tracker'!$I$2:$I$183) -> 0 | F15: =IF(C15=D15,"Completed",IF(C15=0,"Not Started","In Progress")) -> Not Started
A16: 3 | B16: Files, exceptions and reusable code | C16: =COUNTIFS('Daily Tracker'!$A$2:$A$183,A16,'Daily Tracker'!$J$2:$J$183,"Completed") -> 0 | D16: =COUNTIF('Daily Tracker'!$A$2:$A$183,A16) -> 7 | E16: =SUMIF('Daily Tracker'!$A$2:$A$183,A16,'Daily Tracker'!$I$2:$I$183) -> 0 | F16: =IF(C16=D16,"Completed",IF(C16=0,"Not Started","In Progress")) -> Not Started
A17: 4 | B17: Advanced Python fundamentals and testing | C17: =COUNTIFS('Daily Tracker'!$A$2:$A$183,A17,'Daily Tracker'!$J$2:$J$183,"Completed") -> 0 | D17: =COUNTIF('Daily Tracker'!$A$2:$A$183,A17) -> 7 | E17: =SUMIF('Daily Tracker'!$A$2:$A$183,A17,'Daily Tracker'!$I$2:$I$183) -> 0 | F17: =IF(C17=D17,"Completed",IF(C17=0,"Not Started","In Progress")) -> Not Started
A18: 5 | B18: NumPy fundamentals | C18: =COUNTIFS('Daily Tracker'!$A$2:$A$183,A18,'Daily Tracker'!$J$2:$J$183,"Completed") -> 0 | D18: =COUNTIF('Daily Tracker'!$A$2:$A$183,A18) -> 7 | E18: =SUMIF('Daily Tracker'!$A$2:$A$183,A18,'Daily Tracker'!$I$2:$I$183) -> 0 | F18: =IF(C18=D18,"Completed",IF(C18=0,"Not Started","In Progress")) -> Not Started
A19: 6 | B19: Pandas DataFrames and data cleaning | C19: =COUNTIFS('Daily Tracker'!$A$2:$A$183,A19,'Daily Tracker'!$J$2:$J$183,"Completed") -> 0 | D19: =COUNTIF('Daily Tracker'!$A$2:$A$183,A19) -> 7 | E19: =SUMIF('Daily Tracker'!$A$2:$A$183,A19,'Daily Tracker'!$I$2:$I$183) -> 0 | F19: =IF(C19=D19,"Completed",IF(C19=0,"Not Started","In Progress")) -> Not Started
A20: 7 | B20: Advanced Pandas transformations | C20: =COUNTIFS('Daily Tracker'!$A$2:$A$183,A20,'Daily Tracker'!$J$2:$J$183,"Completed") -> 0 | D20: =COUNTIF('Daily Tracker'!$A$2:$A$183,A20) -> 7 | E20: =SUMIF('Daily Tracker'!$A$2:$A$183,A20,'Daily Tracker'!$I$2:$I$183) -> 0 | F20: =IF(C20=D20,"Completed",IF(C20=0,"Not Started","In Progress")) -> Not Started
A21: 8 | B21: Pandas performance and data analysis | C21: =COUNTIFS('Daily Tracker'!$A$2:$A$183,A21,'Daily Tracker'!$J$2:$J$183,"Completed") -> 0 | D21: =COUNTIF('Daily Tracker'!$A$2:$A$183,A21) -> 7 | E21: =SUMIF('Daily Tracker'!$A$2:$A$183,A21,'Daily Tracker'!$I$2:$I$183) -> 0 | F21: =IF(C21=D21,"Completed",IF(C21=0,"Not Started","In Progress")) -> Not Started
A22: 9 | B22: Spark architecture and PySpark setup | C22: =COUNTIFS('Daily Tracker'!$A$2:$A$183,A22,'Daily Tracker'!$J$2:$J$183,"Completed") -> 0 | D22: =COUNTIF('Daily Tracker'!$A$2:$A$183,A22) -> 7 | E22: =SUMIF('Daily Tracker'!$A$2:$A$183,A22,'Daily Tracker'!$I$2:$I$183) -> 0 | F22: =IF(C22=D22,"Completed",IF(C22=0,"Not Started","In Progress")) -> Not Started
A23: 10 | B23: PySpark DataFrame transformations | C23: =COUNTIFS('Daily Tracker'!$A$2:$A$183,A23,'Daily Tracker'!$J$2:$J$183,"Completed") -> 0 | D23: =COUNTIF('Daily Tracker'!$A$2:$A$183,A23) -> 7 | E23: =SUMIF('Daily Tracker'!$A$2:$A$183,A23,'Daily Tracker'!$I$2:$I$183) -> 0 | F23: =IF(C23=D23,"Completed",IF(C23=0,"Not Started","In Progress")) -> Not Started
A24: 11 | B24: Joins, aggregations and windows | C24: =COUNTIFS('Daily Tracker'!$A$2:$A$183,A24,'Daily Tracker'!$J$2:$J$183,"Completed") -> 0 | D24: =COUNTIF('Daily Tracker'!$A$2:$A$183,A24) -> 7 | E24: =SUMIF('Daily Tracker'!$A$2:$A$183,A24,'Daily Tracker'!$I$2:$I$183) -> 0 | F24: =IF(C24=D24,"Completed",IF(C24=0,"Not Started","In Progress")) -> Not Started
A25: 12 | B25: Spark internals and performance | C25: =COUNTIFS('Daily Tracker'!$A$2:$A$183,A25,'Daily Tracker'!$J$2:$J$183,"Completed") -> 0 | D25: =COUNTIF('Daily Tracker'!$A$2:$A$183,A25) -> 7 | E25: =SUMIF('Daily Tracker'!$A$2:$A$183,A25,'Daily Tracker'!$I$2:$I$183) -> 0 | F25: =IF(C25=D25,"Completed",IF(C25=0,"Not Started","In Progress")) -> Not Started
A26: 13 | B26: Advanced PySpark patterns | C26: =COUNTIFS('Daily Tracker'!$A$2:$A$183,A26,'Daily Tracker'!$J$2:$J$183,"Completed") -> 0 | D26: =COUNTIF('Daily Tracker'!$A$2:$A$183,A26) -> 7 | E26: =SUMIF('Daily Tracker'!$A$2:$A$183,A26,'Daily Tracker'!$I$2:$I$183) -> 0 | F26: =IF(C26=D26,"Completed",IF(C26=0,"Not Started","In Progress")) -> Not Started
... A39: 26 | B39: Final deployment and portfolio | C39: =COUNTIFS('Daily Tracker'!$A$2:$A$183,A39,'Daily Tracker'!$J$2:$J$183,"Completed") -> 0 | D39: =COUNTIF('Daily Tracker'!$A$2:$A$183,A39) -> 7 | E39: =SUMIF('Daily Tracker'!$A$2:$A$183,A39,'Daily Tracker'!$I$2:$I$183) -> 0 | F39: =IF(C39=D39,"Completed",IF(C39=0,"Not Started","In Progress")) -> Not Started

Sheet 26-Week Roadmap
A1: Week | B1: Month | C1: Weekly Theme | D1: Core Concepts to Learn | E1: Resources / Practical Exercises | F1: Mini-Project / Deliverable | G1: Completion Evidence | H1: Status | I1: Notes
A2: 1 | B2: Month 1 | C2: Python basics and programming logic | D2: Variables; primitive data types; type conversion; operators; conditionals; loops; notebook/script execution. | E2: Official Python Tutorial; Google Colab or local Python. Exercises: 15–20 small problems on conditions, loops, calculations. | F2: ETL validation utility: validate employee IDs and salaries; separate valid and rejected records. | G2: Runnable script with 10+ test records. | H2: Not Started
A3: 2 | B3: Month 1 | C3: Data structures and functions | D3: Lists, tuples, sets, dictionaries; indexing/slicing; comprehensions; functions; parameters; return values; lambda; scope; nested JSON. | E3: Python tutorial: data structures and functions. Exercises: normalize API-style JSON and write 10 functions. | F3: API response transformer: extract customers, calculate order totals, group orders, identify duplicate IDs. | G3: Reusable Python module with 5+ functions. | H3: Not Started
A4: 3 | B4: Month 1 | C4: Files, exceptions and reusable code | D4: CSV/JSON/text files; exceptions; logging; modules/packages; virtual environments; type hints; docstrings; OOP basics. | E4: Python standard library docs. Exercises: malformed files, invalid values, missing files, line-by-line processing. | F4: File-based ETL framework: read CSVs, validate schemas, consolidate outputs, quarantine rejects. | G4: Configurable pipeline with logs and exception handling. | H4: Not Started
A5: 4 | B5: Month 1 | C5: Advanced Python fundamentals and testing | D5: Iterators/generators; decorators; context managers; shallow/deep copy; pytest; mocking basics; Git basics. | E5: pytest docs and GitHub Skills. Exercises: tests for ETL utility and chunked file processing. | F5: Production-style CSV processing package split into ingestion, validation, transformation, logging and config. | G5: Git repository with tests, README, sample input/output. | H5: Not Started
A6: 5 | B6: Month 2 | C6: NumPy fundamentals | D6: ndarray; shape/dimensions; indexing; reshaping; broadcasting; vectorization; Boolean masks; aggregations; statistics. | E6: NumPy beginner guide. Compare loops with vectorized operations on transaction data. | F6: Transaction analytics engine for revenue, averages, outliers, percentiles and category summaries. | G6: Notebook comparing loop and vectorized solutions. | H6: Not Started
A7: 6 | B7: Month 2 | C7: Pandas DataFrames and data cleaning | D7: Series/DataFrame/index; CSV/JSON/Excel/Parquet I/O; filtering; sorting; missing values; duplicates; data types; schema checks. | E7: Pandas getting-started tutorials; Kaggle public dataset. Introduce nulls, duplicates and bad types. | F7: Customer data cleansing pipeline standardizing names/emails, handling nulls and duplicates. | G7: Cleaned Parquet dataset plus data-quality report. | H7: Not Started
A8: 7 | B8: Month 2 | C8: Advanced Pandas transformations | D8: groupby/agg/transform/apply; merge/join/concat; pivot/melt; dates; resampling; rolling windows; vectorized strings. | E8: Pandas merging and groupby guides. Solve 15 SQL-style problems in Pandas. | F8: Sales/customer analytics: join orders/customers/products; monthly revenue, repeat purchases, top products, lifetime spend. | G8: Notebook with 8+ validated business metrics. | H8: Not Started
A9: 8 | B9: Month 2 | C9: Pandas performance and data analysis | D9: Memory usage; efficient dtypes; chunked CSV; profiling; plotting; distributions; correlations; outliers; Pandas vs Spark. | E9: Pandas scaling guide. Benchmark increasing dataset sizes and chunked vs full-file processing. | F9: Local data profiler reporting schema, nulls, duplicates, summaries and processing duration. | G9: CLI profiler with chunked processing. | H9: Not Started
A10: 9 | B10: Month 3 | C10: Spark architecture and PySpark setup | D10: Distributed computing; driver/executors; partitions/tasks; SparkSession; lazy evaluation; transformations/actions; schemas; CSV/JSON/Parquet. | E10: Apache Spark overview and SQL/DataFrame guide; Databricks Free Edition where available. Compare SQL/Pandas/PySpark. | F10: First distributed ingestion pipeline with schema, filters and Parquet output. | G10: PySpark notebook with schema, transformations and validation. | H10: Not Started
A11: 10 | B11: Month 3 | C11: PySpark DataFrame transformations | D11: select/filter/withColumn/when; casts; null handling; deduplication; built-in functions; expressions; schema enforcement. | E11: Spark SQL/DataFrame guide. Rewrite 15 Pandas transformations in PySpark. | F11: Transaction cleansing: standardized schema, quarantined invalid rows and rejection reasons. | G11: Parameterized cleansing notebook with explicit schemas. | H11: Not Started
A12: 11 | B12: Month 3 | C12: Joins, aggregations and windows | D12: Inner/left/right/full/semi/anti joins; groupBy/agg; window specs; row_number/rank/dense_rank/lag/lead; business-key deduplication. | E12: PySpark window function docs. Solve SQL interview problems in DataFrames. | F12: Customer 360 with lifetime spend, latest purchase, top products and transaction rankings. | G12: Curated customer analytics table reconciled against SQL. | H12: Not Started
A13: 12 | B13: Month 3 | C13: Spark internals and performance | D13: Narrow/wide transformations; shuffles; jobs/stages/tasks; explain/physical plans; Spark UI; repartition/coalesce; broadcast; cache; skew. | E13: Spark tuning guide. Compare joins and inspect plans, shuffle and runtime metrics. | F13: Performance lab comparing 2–3 implementations of a transformation pipeline. | G13: Reproducible benchmark report with plans and metrics. | H13: Not Started
... A27: 26 | B27: Month 6 | C27: Final deployment and portfolio | D27: Release docs; design trade-offs; Spark troubleshooting; code review; handover; interview practice; measured impact presentation. | E27: Review official Databricks docs; mock interviews on Python, Pandas, PySpark, Spark internals and Delta Lake. | F27: Publish portfolio-ready capstone with README, architecture, tests, benchmarks and deployment steps. | G27: Complete project demo and repository. | H27: Not Started

Sheet Daily Tracker
A1: Week | B1: Month | C1: Day | D1: Suggested Session Focus | E1: Detailed Task / Practice | F1: Weekly Project Connection | G1: Planned Hours | H1: Planned Date | I1: Actual Hours | J1: Status | K1: Evidence / Notes | L1: GitHub Commit / Link
A2: 1 | B2: Month 1 | C2: Day 1 | D2: Learn core concepts | E2: Read/watch the week’s core material and write concise notes. Focus on: Python basics and programming logic. Key topics: Variables; primitive data types; type conversion; operators; conditionals; loops; notebook/script execution. | F2: ETL validation utility: validate employee IDs and salaries; separate valid and rejected records. — session 1/7: scope and plan | G2: 1.5 | I2: 0 | J2: Not Started
A3: 1 | B3: Month 1 | C3: Day 2 | D3: Follow guided examples | E3: Recreate 2–3 examples without copy-pasting; explain each step in your own words. Focus on: Python basics and programming logic. Key topics: Variables; primitive data types; type conversion; operators; conditionals; loops; notebook/script execution. | F3: ETL validation utility: validate employee IDs and salaries; separate valid and rejected records. — session 2/7: examples and setup | G3: 1.5 | I3: 0 | J3: Not Started
A4: 1 | B4: Month 1 | C4: Day 3 | D4: Focused exercises | E4: Solve small exercises related to the week’s key concepts. Focus on: Python basics and programming logic. Key topics: Variables; primitive data types; type conversion; operators; conditionals; loops; notebook/script execution. | F4: ETL validation utility: validate employee IDs and salaries; separate valid and rejected records. — session 3/7: first implementation | G4: 1.5 | I4: 0 | J4: Not Started
A5: 1 | B5: Month 1 | C5: Day 4 | D5: Apply to realistic data | E5: Use a sample dataset; implement transformations and inspect edge cases. Focus on: Python basics and programming logic. Key topics: Variables; primitive data types; type conversion; operators; conditionals; loops; notebook/script execution. | F5: ETL validation utility: validate employee IDs and salaries; separate valid and rejected records. — session 4/7: data transformation | G5: 1.5 | I5: 0 | J5: Not Started
A6: 1 | B6: Month 1 | C6: Day 5 | D6: Debug and deepen | E6: Test nulls, duplicates, invalid input and edge cases; profile or inspect output where relevant. Focus on: Python basics and programming logic. Key topics: Variables; primitive data types; type conversion; operators; conditionals; loops; notebook/script execution. | F6: ETL validation utility: validate employee IDs and salaries; separate valid and rejected records. — session 5/7: edge cases and validation | G6: 1.5 | I6: 0 | J6: Not Started
A7: 1 | B7: Month 1 | C7: Day 6 | D7: Build mini-project | E7: Implement the next part of the weekly mini-project and commit your work to Git. Focus on: Python basics and programming logic. Key topics: Variables; primitive data types; type conversion; operators; conditionals; loops; notebook/script execution. | F7: ETL validation utility: validate employee IDs and salaries; separate valid and rejected records. — session 6/7: implementation and integration | G7: 1.5 | I7: 0 | J7: Not Started
A8: 1 | B8: Month 1 | C8: Day 7 | D8: Review and deliver | E8: Finish deliverable, validate results, write README/notes and record lessons learned. Focus on: Python basics and programming logic. Key topics: Variables; primitive data types; type conversion; operators; conditionals; loops; notebook/script execution. | F8: ETL validation utility: validate employee IDs and salaries; separate valid and rejected records. — session 7/7: final validation and documentation | G8: 1 | I8: 0 | J8: Not Started
A9: 2 | B9: Month 1 | C9: Day 1 | D9: Learn core concepts | E9: Read/watch the week’s core material and write concise notes. Focus on: Data structures and functions. Key topics: Lists, tuples, sets, dictionaries; indexing/slicing; comprehensions; functions; parameters; return values; lambda; scope; nested JSON. | F9: API response transformer: extract customers, calculate order totals, group orders, identify duplicate IDs. — session 1/7: scope and plan | G9: 1.5 | I9: 0 | J9: Not Started
A10: 2 | B10: Month 1 | C10: Day 2 | D10: Follow guided examples | E10: Recreate 2–3 examples without copy-pasting; explain each step in your own words. Focus on: Data structures and functions. Key topics: Lists, tuples, sets, dictionaries; indexing/slicing; comprehensions; functions; parameters; return values; lambda; scope; nested JSON. | F10: API response transformer: extract customers, calculate order totals, group orders, identify duplicate IDs. — session 2/7: examples and setup | G10: 1.5 | I10: 0 | J10: Not Started
A11: 2 | B11: Month 1 | C11: Day 3 | D11: Focused exercises | E11: Solve small exercises related to the week’s key concepts. Focus on: Data structures and functions. Key topics: Lists, tuples, sets, dictionaries; indexing/slicing; comprehensions; functions; parameters; return values; lambda; scope; nested JSON. | F11: API response transformer: extract customers, calculate order totals, group orders, identify duplicate IDs. — session 3/7: first implementation | G11: 1.5 | I11: 0 | J11: Not Started
A12: 2 | B12: Month 1 | C12: Day 4 | D12: Apply to realistic data | E12: Use a sample dataset; implement transformations and inspect edge cases. Focus on: Data structures and functions. Key topics: Lists, tuples, sets, dictionaries; indexing/slicing; comprehensions; functions; parameters; return values; lambda; scope; nested JSON. | F12: API response transformer: extract customers, calculate order totals, group orders, identify duplicate IDs. — session 4/7: data transformation | G12: 1.5 | I12: 0 | J12: Not Started
A13: 2 | B13: Month 1 | C13: Day 5 | D13: Debug and deepen | E13: Test nulls, duplicates, invalid input and edge cases; profile or inspect output where relevant. Focus on: Data structures and functions. Key topics: Lists, tuples, sets, dictionaries; indexing/slicing; comprehensions; functions; parameters; return values; lambda; scope; nested JSON. | F13: API response transformer: extract customers, calculate order totals, group orders, identify duplicate IDs. — session 5/7: edge cases and validation | G13: 1.5 | I13: 0 | J13: Not Started
... A183: 26 | B183: Month 6 | C183: Day 7 | D183: Review and deliver | E183: Finish deliverable, validate results, write README/notes and record lessons learned. Focus on: Final deployment and portfolio. Key topics: Release docs; design trade-offs; Spark troubleshooting; code review; handover; interview practice; measured impact presentation. | F183: Publish portfolio-ready capstone with README, architecture, tests, benchmarks and deployment steps. — session 7/7: final validation and documentation | G183: 1 | I183: 0 | J183: Not Started

Sheet Free Resources
A1: Resource | B1: URL | C1: Relevant Weeks | D1: How to Use It
A2: Python official tutorial | B2: https://docs.python.org/3/tutorial/ | C2: Weeks 1–4 | D2: Core language, data structures, functions, files and modules.
A3: Python standard library | B3: https://docs.python.org/3/library/ | C3: Weeks 3–4 | D3: CSV/JSON, logging, pathlib, testing utilities.
A4: pytest documentation | B4: https://docs.pytest.org/ | C4: Weeks 4, 21–26 | D4: Testing and test organization.
A5: GitHub Skills | B5: https://skills.github.com/ | C5: Throughout | D5: Git, GitHub workflows, repositories and collaboration.
A6: NumPy beginner guide | B6: https://numpy.org/doc/stable/user/absolute_beginners.html | C6: Week 5 | D6: Arrays, indexing, vectorization and aggregations.
A7: Pandas getting started | B7: https://pandas.pydata.org/docs/getting_started/ | C7: Weeks 6–8 | D7: DataFrame basics and common operations.
A8: Pandas scaling guide | B8: https://pandas.pydata.org/docs/user_guide/scale.html | C8: Week 8 | D8: Performance, memory and larger-than-memory data.
A9: Pandas merging guide | B9: https://pandas.pydata.org/docs/user_guide/merging.html | C9: Week 7 | D9: Joins and concatenation.
A10: Pandas groupby guide | B10: https://pandas.pydata.org/docs/user_guide/groupby.html | C10: Week 7 | D10: GroupBy and aggregation.
A11: Apache Spark documentation | B11: https://spark.apache.org/docs/latest/ | C11: Weeks 9–13, 18–19 | D11: Spark fundamentals and APIs.
A12: Spark SQL and DataFrames | B12: https://spark.apache.org/docs/latest/sql-programming-guide.html | C12: Weeks 9–13 | D12: DataFrame API and SQL.
... A26: Google Colab | B26: https://colab.research.google.com/ | C26: Weeks 1–8 | D26: Browser-based Python notebooks.

Sheet GitHub Setup Guide
A1: Create GitHub repository: databricks-data-engineering-journey
A3: Step | B3: Action | C3: Details / Example | D3: Done?
A4: 1 | B4: Create/sign in to GitHub | C4: Open https://github.com/ and sign in, or create an account. Enable two-factor authentication if possible. | D4: Not Started
A5: 2 | B5: Create a new repository | C5: Click the + menu (top-right) → New repository. Repository name: databricks-data-engineering-journey. | D5: Not Started
A6: 3 | B6: Choose visibility | C6: Choose Public if you want a portfolio, or Private while learning. Never upload company/client data, credentials, tokens, or proprietary code. | D6: Not Started
A7: 4 | B7: Initialize repository | C7: Add a README. Optionally add a Python .gitignore and choose a license only if you understand how you want others to reuse your work. | D7: Not Started
A8: 5 | B8: Create repository | C8: Click Create repository. Copy the repository URL shown by GitHub, e.g. https://github.com/YOUR-USERNAME/databricks-data-engineering-journey.git. | D8: Not Started
A9: 6 | B9: Install Git (if using a computer) | C9: Install Git from https://git-scm.com/downloads. Configure your name/email in a terminal: git config --global user.name "Your Name" and git config --global user.email "you@example.com". | D9: Not Started
A10: 7 | B10: Clone the repository | C10: In terminal: git clone https://github.com/YOUR-USERNAME/databricks-data-engineering-journey.git ; then cd databricks-data-engineering-journey. Replace YOUR-USERNAME. | D10: Not Started
A11: 8 | B11: Create a useful folder structure | C11: Create folders: python-foundations/, numpy-pandas/, pyspark/, databricks/, capstone/, notes/. Add a README.md in each substantial project folder. | D11: Not Started
A12: 9 | B12: Add starter files | C12: Create README.md, .gitignore, requirements.txt (or pyproject.toml later), and a projects/README.md. Keep sample data small and non-sensitive. | D12: Not Started
A13: 10 | B13: Make your first commit | C13: Run: git add . ; git commit -m "Set up learning journey repository" ; git push origin main. If Git asks you to authenticate, follow GitHub's current authentication instructions. | D13: Not Started
A14: 11 | B14: Use a weekly workflow | C14: Before a new topic: git pull. Work on a small branch if appropriate, test your code, then commit with a clear message such as "Add week 01 ETL validation utility" and push. | D14: Not Started
... A17: 14 | B17: Publish your capstone | C17: Include architecture diagram, setup instructions, synthetic/public sample data instructions, tests, screenshots that contain no sensitive data, and measured benchmark results. | D17: Not Started
A20: Suggested repository structure
A21: databricks-data-engineering-journey/ ├── README.md ├── .gitignore ├── requirements.txt ├── python-foundations/ │ ├── week-01-etl-validation/ │ └── week-02-json-transformer/ ├── numpy-pandas/ │ ├── week-05-numpy-analytics/ │ └── week-06-customer-cleaning/ ├── pyspark/ │ ├── week-09-ingestion/ │ └── week-12-performance-lab/ ├── databricks/ │ ├── week-15-delta-merge/ │ ├── week-16-medallion-pipeline/ │ └── week-20-workflows/ ├── capstone/ │ ├── notebooks-or-src/ │ ├── tests/ │ ├── docs/ │ └── architecture/ └── notes/
A33: Sample README starter
A34: # Databricks Data Engineering Journey A six-month, 26-week learning portfolio covering Python, NumPy, Pandas, PySpark, Databricks, Delta Lake, testing, orchestration and performance optimization. ## Goals - Practice approximately 10 hours per week. - Build weekly mini-projects with tests and documentation. - Complete an end-to-end lakehouse capstone. ## Repository structure - `python-foundations/`: Python exercises and utilities - `numpy-pandas/`: local data analysis and cleaning - `pyspark/`: distributed transformations and performance labs - `databricks/`: notebooks and Delta Lake projects - `capstone/`: end-to-end project, tests and architecture - `notes/`: concise learning notes and interview preparation ## Safety Only use synthetic, public, or otherwise authorized data. Never commit passwords, tokens, credentials, employer/client data, or proprietary code. ## Progress Update this README as weekly deliverables are completed.
